funlib/math/__init__.py
funlib/math/bitshift.py
funlib/math/cantor.py
funlib.math-0.1.dist-info/LICENSE
funlib.math-0.1.dist-info/METADATA
funlib.math-0.1.dist-info/WHEEL
funlib.math-0.1.dist-info/top_level.txt
funlib.math-0.1.dist-info/RECORD
