Metadata-Version: 2.1
Name: funlib.math
Version: 0.1
Summary: some math functions
Author-email: William Patton <pattonw@hhmi.org>, Jan Funke <funkej@hhmi.org>
License: MIT
Classifier: Programming Language :: Python :: 3
Requires-Python: >=3.7
Provides-Extra: dev
License-File: LICENSE
